{"data":{"markdownRemark":{"html":"<p>Help! It's late and I don't see a good way to get rid of this goto construct:</p>\n<p><code>private void advanceTheTimeCursor( Func&#x3C;DateTime> nextTime, Action uponSuccessfulAdvancement) { loop: var t = nextTime(); if (t > reference) return; uponSuccessfulAdvancement(); pastToPresentCursor = t; goto loop; }</code></p>\n<p>I kinda like it, but somebody said somewhere gotos are considered harmful...</p>","frontmatter":{"date":"September 24, 2009","path":null,"title":"How can I get rid of this goto?","tags":["software-development","csharp"]}}},"pageContext":{"title":"How can I get rid of this goto?"}}