{"pageContext":{"title":"Rf.Sites source code available","previous":{"fields":{"slug":"/2009/09/28/asp-net-mvc-class-action-not-method-action","published":true},"frontmatter":{"title":"ASP.NET MVC: class / action, not method / action","tags":["patterns","libs-and-frameworks","csharp"],"date":"2009/09/28"}},"next":{"fields":{"slug":"/2009/11/26/use-32-and-64bit-oracle-client-in-parallel-on-windows-7-64-bit-for-e-g-net-apps","published":true},"frontmatter":{"title":"Use 32 and 64bit Oracle Client in parallel on Windows 7 64-bit for e.g. .NET Apps","tags":["dotnet","tools"],"date":"2009/11/26"}}}}