{"pageContext":{"title":"Writing azure functions with typescript","previous":{"fields":{"slug":"/2019/02/03/typescript-type-shenanigans-2-specify-at-least-one-property","published":true},"frontmatter":{"title":"Typescript type shenanigans 2: specify at least one property","tags":["web","typescript"],"date":"2019/02/03"}},"next":{"fields":{"slug":"/2019/03/03/innovation-vs-improvement","published":true},"frontmatter":{"title":"Innovation vs Improvement","tags":["software-development"],"date":"2019/03/03"}}}}